AUTHORS.txt
LICENSE.txt
MANIFEST.in
buildhelpers.py
setup.py
./cyrasterize/glrasterizer.c
./cyrasterize/glrasterizer.cpp
./cyrasterize/cpp/glr.cpp
./cyrasterize/cpp/glrasterizer.cpp
./cyrasterize/cpp/glrglfw.cpp
cyrasterize/__init__.py
cyrasterize/base.py
cyrasterize/glrasterizer.pyx
cyrasterize.egg-info/PKG-INFO
cyrasterize.egg-info/SOURCES.txt
cyrasterize.egg-info/dependency_links.txt
cyrasterize.egg-info/requires.txt
cyrasterize.egg-info/top_level.txt
cyrasterize/c/shaders.h
cyrasterize/cpp/glr.h
cyrasterize/cpp/glrasterizer.h
cyrasterize/cpp/glrglfw.h
cyrasterize/cpp/shaders.h
cyrasterize/shaders/interactive.frag
cyrasterize/shaders/interactive.vert
cyrasterize/shaders/texture_shader.frag
cyrasterize/shaders/texture_shader.vert