Metadata-Version: 1.1
Name: cyrasterize
Version: 0.1.5
Summary: Simple fast OpenGL offscreen rasterizing in Python
Home-page: https://github.com/menpo/cyrasterize/
Author: James Booth
Author-email: james.booth08@imperial.ac.uk
License: UNKNOWN
Platform: UNKNOWN
Classifier: Development Status :: 3 - Alpha
Classifier: Intended Audience :: Developers
Classifier: Intended Audience :: Science/Research
Classifier: License :: OSI Approved :: BSD License
Classifier: Operating System :: OS Independent
Classifier: Programming Language :: C
Classifier: Programming Language :: Cython
Classifier: Programming Language :: Python :: 2
Classifier: Programming Language :: Python :: 2.7
